czdb/__init__.py
czdb/db_searcher.py
czdb/entity/__init__.py
czdb/entity/data_block.py
czdb/entity/decrypted_block.py
czdb/entity/header_block.py
czdb/entity/hyper_header_block.py
czdb/entity/index_block.py
czdb/utils/__init__.py
czdb/utils/byte_util.py
czdb/utils/decryptor.py
czdb/utils/hyper_header_decoder.py
czdb_searcher-0.1.2.dist-info/METADATA
czdb_searcher-0.1.2.dist-info/WHEEL
czdb_searcher-0.1.2.dist-info/licenses/LICENSE
czdb_searcher-0.1.2.dist-info/RECORD
