Metadata-Version: 2.4
Name: czdb-searcher
Version: 0.1.2
Summary: A Python library for efficient IP geolocation lookup using CZDB database
Project-URL: Homepage, https://github.com/tagphi/czdb_searcher_python
Project-URL: Bug Tracker, https://github.com/tagphi/czdb_searcher_python/issues
Author-email: Liu Cong <cong.liu@rtbasia.com>
License:                                  Apache License
License-File: LICENSE
Classifier: License :: OSI Approved :: Apache Software License
Classifier: Operating System :: OS Independent
Classifier: Programming Language :: Python :: 3
Classifier: Topic :: Internet
Classifier: Topic :: Software Development :: Libraries :: Python Modules
Requires-Python: >=3.7
Requires-Dist: msgpack
Requires-Dist: pycryptodome
